articleparser/__init__.py
articleparser/article.py
articleparser/cleaner.py
articleparser/config.py
articleparser/extractor.py
articleparser/metadata.py
articleparser/settings.py
articleparser/util.py
articleparser/version.py
articleparser-0.1.4.dist-info/LICENSE
articleparser-0.1.4.dist-info/METADATA
articleparser-0.1.4.dist-info/WHEEL
articleparser-0.1.4.dist-info/top_level.txt
articleparser-0.1.4.dist-info/RECORD
