Metadata-Version: 2.1
Name: articleparser
Version: 0.1.4
Summary: Extracts structured data from web articles.
Home-page: https://github.com/sean-lo/articleparser
Author: Sean Lo
Author-email: seanlo96@hotmail.com
License: UNKNOWN
Platform: UNKNOWN
Classifier: Development Status :: 3 - Alpha
Classifier: Programming Language :: Python :: 3
Classifier: License :: OSI Approved :: GNU General Public License v3 (GPLv3)
Classifier: Operating System :: OS Independent
Requires-Python: >=3.8
Requires-Dist: beautifulsoup4 (>=4.8)
Requires-Dist: django (>=3.0)
Requires-Dist: html5lib (>=1.1)
Requires-Dist: language-tags (>=1.0.0)
Requires-Dist: lxml (>=4.5.0)
Requires-Dist: python-dateutil (>=2.8.0)
